[
  {
    "round": 1,
    "teacherReplyText": "真好，愿意动脑思考是最好的！\n\n我们先理清楚这道题的已知条件是什么？可以告诉老师，题目中分别告诉了我们桃树、梨树和苹果树的什么信息吗？",
    "studentRawOutput": "{\"decision\":\"follow_up\",\"question\":\"桃树 24 棵，梨树是桃树的 3 倍，苹果树是梨树的 4 倍，我梳理得对吗？\",\"reason\":\"原始目标包含解题和引导式互动，目前仅刚开始梳理条件，题目未解，互动未完成。\",\"unmet_goals\":[\"计算出苹果树的数量\",\"完成引导式解题过程\"]}",
    "parsedDecision": {
      "type": "follow_up",
      "question": "桃树 24 棵，梨树是桃树的 3 倍，苹果树是梨树的 4 倍，我梳理得对吗？",
      "reason": "原始目标包含解题和引导式互动，目前仅刚开始梳理条件，题目未解，互动未完成。",
      "unmetGoals": [
        "计算出苹果树的数量",
        "完成引导式解题过程"
      ]
    }
  },
  {
    "round": 2,
    "teacherReplyText": "对的，梳理得很清晰！\n\n那我们先来解决第一步：梨树有多少棵呢？（提示：梨树和桃树是什么关系？）",
    "studentRawOutput": "{\"decision\":\"follow_up\",\"question\":\"梨树是 24×3=72 棵对吗？那接下来该怎么算苹果树？\",\"reason\":\"题目尚未解完，正处于引导式解题环节，需回答当前问题并请求下一步\",\"unmet_goals\":[\"完成梨树棵数确认\",\"完成苹果树棵数计算\",\"得出最终答案\"]}",
    "parsedDecision": {
      "type": "follow_up",
      "question": "梨树是 24×3=72 棵对吗？那接下来该怎么算苹果树？",
      "reason": "题目尚未解完，正处于引导式解题环节，需回答当前问题并请求下一步",
      "unmetGoals": [
        "完成梨树棵数确认",
        "完成苹果树棵数计算",
        "得出最终答案"
      ]
    }
  },
  {
    "round": 3,
    "teacherReplyText": "完全正确！梨树就是72棵。\n\n现在来看苹果树——题目说苹果树是梨树的4倍，那你觉得苹果树该怎么算呢？",
    "studentRawOutput": "{\"decision\":\"follow_up\",\"question\":\"那苹果树就是 72×4=288 棵，这道题应该解完了吧？\",\"reason\":\"学生尚未给出最终计算结果，解题过程未闭环，需要回答老师提问以完成目标。\",\"unmet_goals\":[\"完成苹果树数量的计算并确认解题完成\"]}",
    "parsedDecision": {
      "type": "follow_up",
      "question": "那苹果树就是 72×4=288 棵，这道题应该解完了吧？",
      "reason": "学生尚未给出最终计算结果，解题过程未闭环，需要回答老师提问以完成目标。",
      "unmetGoals": [
        "完成苹果树数量的计算并确认解题完成"
      ]
    }
  }
]
