[
  {
    "round": 1,
    "teacherReplyText": "你好！刚考完除法，辛苦啦！你提前想预习小数，这个想法特别好。\n\n其实，小数就在你的生活里。\n\n**什么是小数呢？**\n\n小数就是用来表示\"一个东西的某一部分\"的数。\n\n比如：\n* 半块巧克力是 **0.5** 块，也可以写成 $\\frac{1}{2}$ 块\n* 一支铅笔1元5角，可以写成 **1.5** 元\n* 你的身高如果是1米35厘米，也可以写成 **1.35** 米\n\n**它和分数很像**\n\n我们学过的 $\\frac{1}{2}$（二分之一），用小数写就是 **0.5**。\n\n所以小数其实就是分数的另一种写法，但比分数更方便，比如3.14，如果写成分数就会很长一串。\n\n**你来想一想**\n\n除了刚才老师说的那些，你的生活里还在哪里见到过带\"点\"的数字呢？超市的标签上？尺子上？\n\n小数不难的，等你正式学的时候，你会发现它和整数很像，只是多了一个小数点而已！",
    "studentRawOutput": "{\"decision\":\"follow_up\",\"question\":\"我在超市价格标签上经常见到，那这些小数应该怎么读呢？\",\"reason\":\"概念已初步了解，但预习还需掌握读写方法和数位含义，且老师末尾有互动提问\",\"unmet_goals\":[\"掌握小数的读写方法\",\"理解小数各数位的含义\"]}",
    "parsedDecision": {
      "type": "follow_up",
      "question": "我在超市价格标签上经常见到，那这些小数应该怎么读呢？",
      "reason": "概念已初步了解，但预习还需掌握读写方法和数位含义，且老师末尾有互动提问",
      "unmetGoals": [
        "掌握小数的读写方法",
        "理解小数各数位的含义"
      ]
    }
  },
  {
    "round": 2,
    "teacherReplyText": "对的，超市里最常见的就是价格了！来，老师教你怎么读。\n\n**读法很简单，记住这个顺口溜：**\n\n> \"整数部分按整数读，小数点读成'点'，小数部分逐个读。\"\n\n**举几个例子你看看：**\n\n| 价格标签 | 读作 | 千万别读成 |\n|---------|------|-----------|\n| 2.50 元 | 二点五零元 | ❌ 二点五十元 |\n| 12.99 元 | 十二点九九元 | ❌ 十二点九十九元 |\n| 0.80 元 | 零点八零元 | ❌ 零点八十元 |\n\n**关键提醒：小数部分要一个一个读！**\n\n这就是最容易搞错的地方。整数我们读\"十五\"、\"二十三\"，但小数部分不管有几个数字，都要**拆开单独念**。\n\n比如巧克力标价 **8.88** 元，你要读\"八点八八\"，不能读成\"八点八十八\"哦。\n\n**你来试一试**\n\n你在超市里见过 **3.50** 元这个价格吗？比如一瓶饮料。你现在试着读一遍给老师听听？\n\n读对了吗？\"三点五零\"，很好记的！",
    "studentRawOutput": "{\"decision\":\"follow_up\",\"question\":\"知道了怎么读，那小数应该怎么写呢？\",\"reason\":\"学生已了解概念和读法，但写法尚未学习，属于预习必要环节，且剩余轮次充足\",\"unmet_goals\":[\"学习小数的写法\"]}",
    "parsedDecision": {
      "type": "follow_up",
      "question": "知道了怎么读，那小数应该怎么写呢？",
      "reason": "学生已了解概念和读法，但写法尚未学习，属于预习必要环节，且剩余轮次充足",
      "unmetGoals": [
        "学习小数的写法"
      ]
    }
  },
  {
    "round": 3,
    "teacherReplyText": "小数的写法其实和读法是配套的，你记住**\"先写整数，再写点，最后写小数\"**这三个步骤就行。\n\n**举个例子：**\n\n\"二点三五米\"怎么写？\n\n**第一步：写整数部分**\n\"二\" → 写 **2**\n\n**第二步：写小数点**\n在2的右下角点一个 **.**\n\n**第三步：写小数部分**\n\"三五\" → 依次写 **35**\n\n合起来：**2.35**\n\n**再来一个：**\n\n\"零点八元\"\n- 整数部分是\"零\" → **0**\n- 小数点 → **.**\n- 小数部分\"八\" → **8**\n- 合起来：**0.8**\n\n**最容易错的地方：整数部分是0时别忘了写0！**\n\n有的同学写\"零点八\"时，就只写 **.8**，这是不对的。一定要写成 **0.8**，完整的写法才行。\n\n**给你一个小思考题**\n\n如果你在超市里看到标签上写着 \"三点零五\"，你知道这个价钱用小数该怎么写吗？⸻",
    "studentRawOutput": "{\"decision\":\"follow_up\",\"question\":\"是 3.05 元吗？那小数之间怎么比大小呢？\",\"reason\":\"老师最后留下了练习题需要反馈，且小数比较大小是预习的重要内容尚未学习\",\"unmet_goals\":[\"确认写法练习答案\",\"学习小数大小比较\"]}",
    "parsedDecision": {
      "type": "follow_up",
      "question": "是 3.05 元吗？那小数之间怎么比大小呢？",
      "reason": "老师最后留下了练习题需要反馈，且小数比较大小是预习的重要内容尚未学习",
      "unmetGoals": [
        "确认写法练习答案",
        "学习小数大小比较"
      ]
    }
  }
]
